py_process
