Metadata-Version: 2.1
Name: py-process
Version: 0.0.2
Summary: engine processs
Home-page: https://github.com/FlavioLionelRita/py-process
Author: Flavio Lionel Rita
Author-email: flaviolrita@hotmail.com
License: UNKNOWN
Download-URL: https://github.com/FlavioLionelRita/py-process/tarball/0.0.2
Keywords: process,business process,bpm,bpmn,engine
Platform: UNKNOWN
